LICENSE
MANIFEST.in
setup.cfg
setup.py
facsimile/VERSION
facsimile/requirements-docs.txt
facsimile/requirements-test.txt
facsimile/requirements.txt
ngage/__init__.py
ngage/cli.py
ngage/config.py
ngage/exceptions.py
ngage.egg-info/PKG-INFO
ngage.egg-info/SOURCES.txt
ngage.egg-info/dependency_links.txt
ngage.egg-info/entry_points.txt
ngage.egg-info/requires.txt
ngage.egg-info/top_level.txt
ngage.egg-info/zip-safe
ngage/plugins/__init__.py
ngage/plugins/eznc.py
ngage/plugins/napalm.py