Metadata-Version: 1.1
Name: ngage
Version: 0.1.0
Summary: network device config twirler
Home-page: UNKNOWN
Author: 20C
Author-email: code@20c.com
License: UNKNOWN
Platform: UNKNOWN
Classifier: Development Status :: 4 - Beta
